pyvisalgo/__init__.py
pyvisalgo/array.py
pyvisalgo/array_sort.py
pyvisalgo/base.py
pyvisalgo/bins.py
pyvisalgo/color.py
pyvisalgo/dummy.py
pyvisalgo/dynamic.py
pyvisalgo/knight.py
pyvisalgo/planar.py
pyvisalgo/plane_closest.py
pyvisalgo/plane_euler.py
pyvisalgo/welzl.py
pyvisalgo-0.1.1.dist-info/licenses/LICENSE
pyvisalgo-0.1.1.dist-info/METADATA
pyvisalgo-0.1.1.dist-info/WHEEL
pyvisalgo-0.1.1.dist-info/top_level.txt
pyvisalgo-0.1.1.dist-info/RECORD
