Metadata-Version: 2.4
Name: pyvisalgo
Version: 0.1.1
Summary: Python-based algorithm visualization framework for teaching.
Author: Kiyong Kim
Classifier: Programming Language :: Python :: 3
Classifier: Operating System :: OS Independent
Requires-Python: >=3.7
License-File: LICENSE
Requires-Dist: pygame
Dynamic: author
Dynamic: classifier
Dynamic: description
Dynamic: description-content-type
Dynamic: license-file
Dynamic: requires-dist
Dynamic: requires-python
Dynamic: summary
